{
    "ntrain": 6000000,
    "nval": 2000000,
    "log_r_val": 479.7541769221425,
    "best_iteration": 500,
    "best_quality": {
        "mean": 0.00023987708846107125,
        "sdev": 1.5151995285123121e-05
    },
    "iteration_to_quality": {
        "50": {
            "mean": 0.00016959570348262787,
            "sdev": 7.718539563938975e-06
        },
        "100": {
            "mean": 0.00022487576643470675,
            "sdev": 1.1044506209145766e-05
        },
        "150": {
            "mean": 0.00022495593293569982,
            "sdev": 1.144391262641875e-05
        },
        "200": {
            "mean": 0.00023304011847358197,
            "sdev": 1.2239468560437672e-05
        },
        "250": {
            "mean": 0.00023037393111735582,
            "sdev": 1.2452231203496922e-05
        },
        "300": {
            "mean": 0.0002311565913259983,
            "sdev": 1.3011401279072743e-05
        },
        "350": {
            "mean": 0.00023745895305182785,
            "sdev": 1.374294970446499e-05
        },
        "400": {
            "mean": 0.00023674065596424043,
            "sdev": 1.4219848708307836e-05
        },
        "450": {
            "mean": 0.0002367762353969738,
            "sdev": 1.4535994523612317e-05
        },
        "500": {
            "mean": 0.00023987708846107125,
            "sdev": 1.5151995285123121e-05
        },
        "550": {
            "mean": 0.00023807324760127813,
            "sdev": 1.5302641259040684e-05
        },
        "600": {
            "mean": 0.0002359812060603872,
            "sdev": 1.5393497960758395e-05
        },
        "650": {
            "mean": 0.0002333455631742254,
            "sdev": 1.5490228179260157e-05
        },
        "700": {
            "mean": 0.000230593272135593,
            "sdev": 1.558844087412581e-05
        },
        "750": {
            "mean": 0.000229651530389674,
            "sdev": 1.5763826013426296e-05
        },
        "800": {
            "mean": 0.00023126609448809177,
            "sdev": 1.6188823792617768e-05
        },
        "850": {
            "mean": 0.00022962584625929594,
            "sdev": 1.6522171790711582e-05
        },
        "900": {
            "mean": 0.00022688947501592338,
            "sdev": 1.667551987338811e-05
        },
        "950": {
            "mean": 0.00022687648015562445,
            "sdev": 1.696917024673894e-05
        },
        "1000": {
            "mean": 0.00022583352983929217,
            "sdev": 1.704718124528881e-05
        }
    },
    "tag": {
        "datapath": "/r04/atlas/symmetries/data/truth_ktdurham200_cut/liv_3j_4j_p16",
        "with_flav": true,
        "with_hel": true
    }
}