{
    "ntrain": 6000000,
    "nval": 2000000,
    "log_r_val": -9.716750355437398,
    "best_iteration": 50,
    "best_quality": {
        "mean": -4.858375177718699e-06,
        "sdev": 3.098860588579555e-06
    },
    "iteration_to_quality": {
        "50": {
            "mean": -4.858375177718699e-06,
            "sdev": 3.098860588579555e-06
        },
        "100": {
            "mean": -9.980574759538285e-06,
            "sdev": 4.126423846173566e-06
        },
        "150": {
            "mean": -1.4200004443409853e-05,
            "sdev": 5.045525995228672e-06
        },
        "200": {
            "mean": -1.6670144759700634e-05,
            "sdev": 5.486905138241127e-06
        },
        "250": {
            "mean": -2.4641551135573536e-05,
            "sdev": 6.255769221752416e-06
        },
        "300": {
            "mean": -3.0363600671989843e-05,
            "sdev": 6.814415883127367e-06
        },
        "350": {
            "mean": -3.448682764428668e-05,
            "sdev": 7.282306341949152e-06
        },
        "400": {
            "mean": -4.02042678615544e-05,
            "sdev": 7.772599019517656e-06
        },
        "450": {
            "mean": -4.3445317714940757e-05,
            "sdev": 8.091946256172378e-06
        },
        "500": {
            "mean": -4.7089630243135616e-05,
            "sdev": 8.429752597294282e-06
        },
        "550": {
            "mean": -4.993544644094072e-05,
            "sdev": 8.591886398789939e-06
        },
        "600": {
            "mean": -5.364459866541438e-05,
            "sdev": 8.867569704307243e-06
        },
        "650": {
            "mean": -5.479208266478963e-05,
            "sdev": 8.972822797659319e-06
        },
        "700": {
            "mean": -5.843364488100633e-05,
            "sdev": 9.183080692309886e-06
        },
        "750": {
            "mean": -6.264732655836269e-05,
            "sdev": 9.428243174625095e-06
        },
        "800": {
            "mean": -6.52825619908981e-05,
            "sdev": 9.696066626929678e-06
        },
        "850": {
            "mean": -6.921942258486524e-05,
            "sdev": 9.985293218051083e-06
        },
        "900": {
            "mean": -7.674875814700499e-05,
            "sdev": 1.0302343071089126e-05
        },
        "950": {
            "mean": -8.011441241251305e-05,
            "sdev": 1.0562755051068962e-05
        },
        "1000": {
            "mean": -8.396541670663282e-05,
            "sdev": 1.0750912224466447e-05
        }
    },
    "tag": {
        "datapath": "/r04/atlas/symmetries/data/truth_ktdurham200_cut/liv_3j_4j_p09",
        "with_flav": false,
        "with_hel": false
    }
}